geomockimages/__init__.py
geomockimages/imagecreator.py
geomockimages/logging.py
geomockimages/raster.py
geomockimages/test/__init__.py
geomockimages/test/test_geomockimages.py
geomockimages-0.2.4.dist-info/LICENSE
geomockimages-0.2.4.dist-info/WHEEL
geomockimages-0.2.4.dist-info/METADATA
geomockimages-0.2.4.dist-info/RECORD
