Metadata-Version: 2.1
Name: geomockimages
Version: 0.2.4
Summary: A module to programmatically create geotiff images which can be used for unit tests.
Home-page: https://github.com/markusuwe/geomockimages
License: MIT
Author: Markus Müller
Author-email: markus.u.mueller@zoho.com
Requires-Python: >=3.10,<4.0
Classifier: License :: OSI Approved :: MIT License
Classifier: Programming Language :: Python :: 3
Classifier: Programming Language :: Python :: 3.10
Classifier: Programming Language :: Python :: 3.11
Requires-Dist: numpy (>=1.26.4,<2.0.0)
Requires-Dist: rasterio (>=1.3.10,<2.0.0)
Requires-Dist: rio-cogeo (>=5.3.0,<6.0.0)
Requires-Dist: scikit-image (>=0.23.2,<0.24.0)
Requires-Dist: scipy (>=1.13.0,<2.0.0)
Project-URL: Repository, https://github.com/markusuwe/geomockimages
